itaxotools/__pyinstaller/hook-itaxotools.blastax.py
itaxotools/blastax/__init__.py
itaxotools/blastax/blast.py
itaxotools/blastax/codons.py
itaxotools/blastax/config.py
itaxotools/blastax/core.py
itaxotools/blastax/download.py
itaxotools/blastax/fastmerge.py
itaxotools/blastax/fastsplit.py
itaxotools/blastax/fastutils.py
itaxotools/blastax/main.py
itaxotools/blastax/merge.py
itaxotools/blastax/resources.py
itaxotools/blastax/scafos.py
itaxotools/blastax/translator.py
itaxotools/blastax/utils.py
itaxotools/blastax/documents/about.html
itaxotools/blastax/documents/blast.html
itaxotools/blastax/documents/cutadapt.html
itaxotools/blastax/documents/mafft.html
itaxotools/blastax/documents/museo.html
itaxotools/blastax/graphics/about.svg
itaxotools/blastax/graphics/append.svg
itaxotools/blastax/graphics/appendx.svg
itaxotools/blastax/graphics/blast.svg
itaxotools/blastax/graphics/codon_align.svg
itaxotools/blastax/graphics/create.svg
itaxotools/blastax/graphics/cutadapt.svg
itaxotools/blastax/graphics/decont.svg
itaxotools/blastax/graphics/fastmerge.svg
itaxotools/blastax/graphics/fastsplit.svg
itaxotools/blastax/graphics/groupmerge.svg
itaxotools/blastax/graphics/mafft.svg
itaxotools/blastax/graphics/museo.svg
itaxotools/blastax/graphics/prepare.svg
itaxotools/blastax/graphics/removal.svg
itaxotools/blastax/graphics/scafos.svg
itaxotools/blastax/graphics/translator.svg
itaxotools/blastax/graphics/trim.svg
itaxotools/blastax/logos/blastax.ico
itaxotools/blastax/logos/blastax.svg
itaxotools/blastax/logos/blastax_banner.svg
itaxotools/blastax/logos/blastax_banner_r.svg
itaxotools/blastax/logos/blastax_r.svg
itaxotools/blastax/tasks/about/__init__.py
itaxotools/blastax/tasks/about/model.py
itaxotools/blastax/tasks/about/process.py
itaxotools/blastax/tasks/about/view.py
itaxotools/blastax/tasks/append/__init__.py
itaxotools/blastax/tasks/append/model.py
itaxotools/blastax/tasks/append/process.py
itaxotools/blastax/tasks/append/types.py
itaxotools/blastax/tasks/append/view.py
itaxotools_blastax-0.1.1.dist-info/licenses/LICENSE.txt
itaxotools_blastax-0.1.1.dist-info/METADATA
itaxotools_blastax-0.1.1.dist-info/WHEEL
itaxotools_blastax-0.1.1.dist-info/entry_points.txt
itaxotools_blastax-0.1.1.dist-info/top_level.txt
itaxotools_blastax-0.1.1.dist-info/RECORD
